trails/__init__.py
trails/combine_states.py
trails/cutpoints.py
trails/get_ABC.py
trails/get_emission_prob_mat.py
trails/get_joint_prob_mat.py
trails/get_ordered.py
trails/get_tab.py
trails/get_times.py
trails/load_trans_mat.py
trails/optimizer.py
trails/read_data.py
trails/vanloan.py
trails/data/trans_mat_full_1.csv
trails/data/trans_mat_full_2.csv
trails/data/trans_mat_full_3.csv
trails_rivasiker-0.0.1.dist-info/LICENSE
trails_rivasiker-0.0.1.dist-info/METADATA
trails_rivasiker-0.0.1.dist-info/WHEEL
trails_rivasiker-0.0.1.dist-info/top_level.txt
trails_rivasiker-0.0.1.dist-info/RECORD
