Metadata-Version: 2.1
Name: trails-rivasiker
Version: 0.0.1
Summary: Tree reconstruction of ancestry using incomplete lineage sorting
Home-page: https://github.com/rivasiker/trails
Author: Iker Rivas-González
Author-email: irg@birc.au.dk
Project-URL: Bug Tracker, https://github.com/rivasiker/trails/issues
Classifier: Programming Language :: Python :: 3
Classifier: License :: OSI Approved :: MIT License
Classifier: Operating System :: OS Independent
Requires-Python: >=3.6
License-File: LICENSE
Requires-Dist: numpy
Requires-Dist: pandas
Requires-Dist: scipy
Requires-Dist: ray
Requires-Dist: numba
Requires-Dist: biopython
